trianz/__init__.py
trianz/generator.py
trianz_generator-0.0.1.dist-info/LICENSE.txt
trianz_generator-0.0.1.dist-info/METADATA
trianz_generator-0.0.1.dist-info/WHEEL
trianz_generator-0.0.1.dist-info/top_level.txt
trianz_generator-0.0.1.dist-info/RECORD
